start_ocr/__init__.py
start_ocr/components.py
start_ocr/content.py
start_ocr/coordinates.py
start_ocr/demo.py
start_ocr/fetch.py
start_ocr/logger.py
start_ocr/slice.py
start_ocr-0.0.6.dist-info/METADATA
start_ocr-0.0.6.dist-info/WHEEL
start_ocr-0.0.6.dist-info/top_level.txt
start_ocr-0.0.6.dist-info/RECORD
